hrctui/__init__.py
hrctui/__main__.py
hrctui/api.py
hrctui/crypto.py
hrctui/notifications.py
hrctui/sockets.py
hrctui/pages/chats_page.py
hrctui/pages/login_page.py
hrctui/pages/tcss/chats.tcss
hrctui/pages/tcss/main.tcss
hrctui-0.0.3.dist-info/METADATA
hrctui-0.0.3.dist-info/WHEEL
hrctui-0.0.3.dist-info/licenses/LICENSE
hrctui-0.0.3.dist-info/RECORD
